{
  "teachers": [
    {
      "id": 2,
      "avatar_url": "https://images.unsplash.com/photo-1570295999919-56ceb5ecca61?ixlib=rb-1.2.1&ixid=eyJhcHBfaWQiOjEyMDd9&auto=format&fit=crop&w=500&q=60",
      "name": "Roberto R Svicero",
      "birth": 221702400000,
      "schooling": "superior",
      "classes": "P",
      "services": "Informática, Matemática, Física",
      "created_at": 1602113200395
    },
    {
      "id": 4,
      "avatar_url": "https://i.pinimg.com/236x/9e/8e/c3/9e8ec3c525194846c3b360a6095d5f37.jpg",
      "name": "Diego Fernandes",
      "birth": 4320000000,
      "schooling": "superior",
      "classes": "P",
      "services": "Educação Física, Português",
      "created_at": 1602096583326
    },
    {
      "id": 3,
      "avatar_url": "https://images.unsplash.com/photo-1504911539020-cfb0f7887a5e?ixlib=rb-1.2.1&ixid=eyJhcHBfaWQiOjEyMDd9&auto=format&fit=crop&w=500&q=60",
      "name": "Mary Jane",
      "birth": -132105600000,
      "schooling": "doutorado",
      "classes": "P",
      "services": "Química, História, Geografia",
      "created_at": 1602278727352
    }
  ]
}